pystoreql/__init__.py
pystoreql/compression.py
pystoreql/config.py
pystoreql-0.0.5.dist-info/DESCRIPTION.rst
pystoreql-0.0.5.dist-info/METADATA
pystoreql-0.0.5.dist-info/RECORD
pystoreql-0.0.5.dist-info/WHEEL
pystoreql-0.0.5.dist-info/entry_points.txt
pystoreql-0.0.5.dist-info/metadata.json
pystoreql-0.0.5.dist-info/top_level.txt
