Metadata-Version: 2.0
Name: pystoreql
Version: 0.0.5
Summary: A command line tool to easily share pastes and files.
Home-page: https://github.com/hieu-n/pystoreql
Author: Hieu Nguyen
Author-email: author_email@gmail.com
License: GNU GPLv3
Keywords: some keywords
Platform: UNKNOWN
Classifier: Development Status :: 3 - Alpha
Classifier: Environment :: Console
Classifier: Intended Audience :: Developers
Classifier: Intended Audience :: Science/Research
Classifier: Intended Audience :: System Administrators
Classifier: Topic :: Internet
Classifier: Topic :: System :: Archiving
Classifier: Topic :: Terminals
Classifier: Topic :: Utilities
Classifier: Operating System :: POSIX :: Linux
Classifier: License :: OSI Approved :: GNU General Public License v3 (GPLv3)
Classifier: License :: OSI Approved :: GNU General Public License v3 or later (GPLv3+)
Classifier: Programming Language :: Python :: 2.7
Requires-Dist: docopt
Requires-Dist: pyyaml
Requires-Dist: requests
